[{
        "parent": "01",
        "name": "12"
    },
    {
        "parent": "01",
        "name": "13"
    },
    {
        "parent": "01",
        "name": "14"
    },
    {
        "parent": "0",
        "name": "01"
    },
    {
        "parent": "0",
        "name": "02"
    },
    {
        "parent": "02",
        "name": "21"
    },
    {
        "parent": "02",
        "name": "22"
    },
    {
        "parent": "0",
        "name": "03"
    },
    {
        "parent": "03",
        "name": "31"
    },
    {
        "parent": "03",
        "name": "31"
    },
    {
        "parent": "31",
        "name": "311"
    },
    {
        "parent": "31",
        "name": "312"
    }
]